snvoter/__init__.py
snvoter/__main__.py
snvoter/model/NA12878_20FC_model.h5
snvoter/model/NA12878_20FC_model.h5.pkl
snvoter-1.0.dist-info/LICENSE
snvoter-1.0.dist-info/METADATA
snvoter-1.0.dist-info/WHEEL
snvoter-1.0.dist-info/entry_points.txt
snvoter-1.0.dist-info/top_level.txt
snvoter-1.0.dist-info/RECORD
