Metadata-Version: 2.1
Name: snvoter
Version: 1.0
Summary: A top up tool to enhance SNV calling from Nanopore sequencing data.
Home-page: UNKNOWN
Author: Vahid Akbari
Author-email: vakbari@bcgsc.ca
License: UNKNOWN
Project-URL: GitHub, https://github.com/vahidAK/SNVoter
Platform: UNKNOWN
Classifier: Programming Language :: Python :: 3
Classifier: License :: OSI Approved :: GNU General Public License v3 (GPLv3)
Classifier: Operating System :: Unix
Classifier: Operating System :: POSIX :: Linux
Requires-Python: >=3.7
Requires-Dist: numpy (<1.19.0,>=1.16.0)
Requires-Dist: pandas (>=1.0.3)
Requires-Dist: pysam (>=0.15.4)
Requires-Dist: tqdm (>=4.36.1)
Requires-Dist: tensorflow (>=2.1.0)
Requires-Dist: keras (>=2.2.4)
Requires-Dist: matplotlib (>=3.3.0)
Requires-Dist: multiprocess (>=0.70.10)
Requires-Dist: scikit-learn (>=0.21.3)
